[{"comment": "\"I liked most: the practical case scenarios that apply theoretical knowledge to real clinical situations. Interactive components, such as simulations or role-play, which help reinforce communication and critical thinking skills. Coverage of patient safety and error prevention strategies. Discussions on handling ethical dilemmas and vulnerable populations, which are highly relevant to real-world practice.\"", "profession": "Physician", "country": "Brazil", "stars": "5"}, {"comment": "\"I enjoyed learning more about new communication skills.\"", "profession": "Nurse", "country": "Pakistan", "stars": "5"}, {"comment": "\"I liked the video lectures and visual animation images.\"", "profession": "Anaesthesiologist", "country": "Pakistan", "stars": "5"}, {"comment": "\"A nice summary of available knowledge.\"", "profession": "Specialist Surgeon", "country": "India", "stars": "4"}]